rbenchpoc/__init__.py
rbenchpoc/rbenchpoc.py
rbenchpoc-0.1.1.dist-info/METADATA
rbenchpoc-0.1.1.dist-info/WHEEL
rbenchpoc-0.1.1.dist-info/top_level.txt
rbenchpoc-0.1.1.dist-info/RECORD
