Metadata-Version: 2.1
Name: rbenchpoc
Version: 0.1.1
Requires-Dist: transformers
Requires-Dist: bert-score
Requires-Dist: pandas
Requires-Dist: tqdm
Requires-Dist: click
